nacos_test/__init__.py
nacos_test/pynacos.py
nacos_test/common/__init__.py
nacos_test/common/common.py
nacos_test-1.0.dist-info/METADATA
nacos_test-1.0.dist-info/WHEEL
nacos_test-1.0.dist-info/top_level.txt
nacos_test-1.0.dist-info/RECORD
