Metadata-Version: 2.1
Name: nacos-test
Version: 1.0
Requires-Dist: nacos-sdk-python (==0.1.6)
